qSide/__init__.py
qSide/action.cp311-win_amd64.pyd
qSide/action.pyi
qSide/app.cp311-win_amd64.pyd
qSide/app.pyi
qSide/breadcrumb.cp311-win_amd64.pyd
qSide/breadcrumb.pyi
qSide/colorpick.cp311-win_amd64.pyd
qSide/colorpick.pyi
qSide/config.cp311-win_amd64.pyd
qSide/config.pyi
qSide/document.cp311-win_amd64.pyd
qSide/document.pyi
qSide/fontfamily.cp311-win_amd64.pyd
qSide/fontfamily.pyi
qSide/infobadge.cp311-win_amd64.pyd
qSide/infobadge.pyi
qSide/inputdialog.cp311-win_amd64.pyd
qSide/inputdialog.pyi
qSide/itemdelegate.cp311-win_amd64.pyd
qSide/itemdelegate.pyi
qSide/label.cp311-win_amd64.pyd
qSide/label.pyi
qSide/layout.cp311-win_amd64.pyd
qSide/layout.pyi
qSide/libraryinfo.cp311-win_amd64.pyd
qSide/libraryinfo.pyi
qSide/lineedit.cp311-win_amd64.pyd
qSide/lineedit.pyi
qSide/listwidget.cp311-win_amd64.pyd
qSide/listwidget.pyi
qSide/logging.cp311-win_amd64.pyd
qSide/logging.pyi
qSide/mainwindow.cp311-win_amd64.pyd
qSide/mainwindow.pyi
qSide/menu.cp311-win_amd64.pyd
qSide/menu.pyi
qSide/messagebox.cp311-win_amd64.pyd
qSide/messagebox.pyi
qSide/pushbutton.cp311-win_amd64.pyd
qSide/pushbutton.pyi
qSide/python_ext.cp311-win_amd64.pyd
qSide/python_ext.pyi
qSide/qt.cp311-win_amd64.pyd
qSide/qt.pyi
qSide/screen.cp311-win_amd64.pyd
qSide/screen.pyi
qSide/scrollbar.cp311-win_amd64.pyd
qSide/scrollbar.pyi
qSide/seperator.cp311-win_amd64.pyd
qSide/seperator.pyi
qSide/spacer.cp311-win_amd64.pyd
qSide/spacer.pyi
qSide/statetooltip.cp311-win_amd64.pyd
qSide/statetooltip.pyi
qSide/stylesheet.cp311-win_amd64.pyd
qSide/stylesheet.pyi
qSide/tabwidget.cp311-win_amd64.pyd
qSide/tabwidget.pyi
qSide/textcursor.cp311-win_amd64.pyd
qSide/textcursor.pyi
qSide/theme.cp311-win_amd64.pyd
qSide/theme.pyi
qSide/toolbutton.cp311-win_amd64.pyd
qSide/toolbutton.pyi
qSide/tooltip.cp311-win_amd64.pyd
qSide/tooltip.pyi
qSide/treeview.cp311-win_amd64.pyd
qSide/treeview.pyi
qSide/treewidget.cp311-win_amd64.pyd
qSide/treewidget.pyi
qSide/_rc/fonts/JetBrainsMono-Bold.ttf
qside-2025.10.15.dist-info/METADATA
qside-2025.10.15.dist-info/WHEEL
qside-2025.10.15.dist-info/top_level.txt
qside-2025.10.15.dist-info/RECORD
