Metadata-Version: 2.4
Name: qSide
Version: 2025.10.15
Summary: Qt framework.
Home-page: 
Author: Connet Information Technology Company Ltd, Shanghai.
Author-email: tech_support@shconnet.com.cn
Keywords: Qt Python
Classifier: Intended Audience :: Developers
Classifier: Programming Language :: Python
Classifier: Programming Language :: Python :: 3.6
Classifier: Programming Language :: Python :: 3.7
Classifier: Programming Language :: Python :: 3.8
Classifier: Programming Language :: Python :: 3.9
Classifier: Programming Language :: Python :: 3.10
Classifier: Programming Language :: Python :: 3.11
Classifier: Programming Language :: Python :: Implementation :: CPython
Classifier: Topic :: Software Development :: Interpreters
Requires-Dist: darkdetect; sys_platform == "win32"
Requires-Dist: darkdetect[macos-listener]; sys_platform == "darwin"
Requires-Dist: qtpy
Requires-Dist: qdarkstyle
Requires-Dist: qstylizer
Requires-Dist: PySide6
Requires-Dist: pyobjc-framework-Cocoa; sys_platform == "darwin"
Requires-Dist: pyobjc-framework-Quartz; sys_platform == "darwin"
Requires-Dist: pywin32==304; sys_platform == "win32"
Requires-Dist: tree-sitter
Requires-Dist: tree-sitter-python
Dynamic: author
Dynamic: author-email
Dynamic: classifier
Dynamic: description-content-type
Dynamic: keywords
Dynamic: requires-dist
Dynamic: summary
